agentic_ai_vass_tools/__init__.py
agentic_ai_vass_tools/models/connector_info.py
agentic_ai_vass_tools/models/odata_endpoint_info.py
agentic_ai_vass_tools/models/query_tool_input.py
agentic_ai_vass_tools/services/sap_connector_service.py
agentic_ai_vass_tools/tools/odata_date_formatter_tools.py
agentic_ai_vass_tools/tools/odata_query_tool.py
agentic_ai_vass_tools/utils/api_utils.py
agentic_ai_vass_tools/utils/btp_utils.py
agentic_ai_vass_tools-0.4.dist-info/licenses/LICENSE
agentic_ai_vass_tools-0.4.dist-info/METADATA
agentic_ai_vass_tools-0.4.dist-info/WHEEL
agentic_ai_vass_tools-0.4.dist-info/top_level.txt
agentic_ai_vass_tools-0.4.dist-info/RECORD
