Metadata-Version: 2.4
Name: agentic-ai-vass-tools
Version: 0.4
Summary: provide SAP agentic AI tools
Author: Emanuele Dalessandro
License-Expression: Apache-2.0
Project-URL: Homepage, https://github.com/emadal95/agentic-ai-vass-tools
Project-URL: Changelog, https://github.com/emadal95/agentic-ai-vass-tools/releases
Project-URL: Issues, https://github.com/emadal95/agentic-ai-vass-tools/issues
Project-URL: CI, https://github.com/emadal95/agentic-ai-vass-tools/actions
Requires-Python: >=3.8
License-File: LICENSE
Requires-Dist: flask==3.0.0
Requires-Dist: flask-cors==5.0.1
Requires-Dist: werkzeug==3.0.1
Requires-Dist: crewai[tools]==0.100.0
Requires-Dist: crewai==0.100.0
Requires-Dist: xmltodict
Requires-Dist: requests
Requires-Dist: cfenv
Provides-Extra: test
Requires-Dist: pytest; extra == "test"
Dynamic: license-file
